media_composer/__init__.py
media_composer-0.1.0.dist-info/METADATA
media_composer-0.1.0.dist-info/WHEEL
media_composer-0.1.0.dist-info/top_level.txt
media_composer-0.1.0.dist-info/RECORD
