Metadata-Version: 2.4
Name: media_composer
Version: 0.1.0
Summary: 音视频合成处理工具包
Author-email: Your Name <your@email.com>
Project-URL: Homepage, https://github.com/yourusername/media-composer
Classifier: Programming Language :: Python :: 3
Classifier: License :: OSI Approved :: MIT License
Classifier: Operating System :: OS Independent
Requires-Python: >=3.8
Requires-Dist: moviepy
Requires-Dist: requests
Requires-Dist: python-dotenv
